safeqthreads/__init__.py
safeqthreads/descriptors.py
safeqthreads/errors.py
safeqthreads/safeQThreads.py
tests/__init__.py
tests/test_descriptors.py
tests/test_errors.py
tests/test_safeqthreads.py
safeqthreads-0.0.2.dist-info/LICENSE
safeqthreads-0.0.2.dist-info/METADATA
safeqthreads-0.0.2.dist-info/WHEEL
safeqthreads-0.0.2.dist-info/top_level.txt
safeqthreads-0.0.2.dist-info/RECORD
