Metadata-Version: 2.1
Name: safeqthreads
Version: 0.0.2
Summary: Track and manage your QThreads.
Home-page: https://github.com/simongarisch/safeqthreads
Author: Simon Garisch
Author-email: gatman946@gmail.com
License: UNKNOWN
Platform: UNKNOWN
Requires-Dist: QtPy (>=1.5.0)
